cyobj/__init__.py
cyobj/io.py
cyobj/detail/io.cpython-36m-x86_64-linux-gnu.so
cyobj-0.2.3.dist-info/WHEEL
cyobj-0.2.3.dist-info/top_level.txt
cyobj-0.2.3.dist-info/LICENSE
cyobj-0.2.3.dist-info/RECORD
cyobj-0.2.3.dist-info/METADATA
