Metadata-Version: 2.1
Name: cyobj
Version: 0.2.3
Summary: A fast and Wavefront .OBJ reader/writer
Home-page: https://github.com/ycjungSubhuman/cyobj
Author: Yucheol Jung
Author-email: ycjung@postech.ac.kr
License: UNKNOWN
Platform: UNKNOWN
License-File: LICENSE
